types_yt_dlp-2026.1.29.20260131.dist-info/licenses/LICENSE
yt_dlp-stubs/METADATA.toml
yt_dlp-stubs/YoutubeDL.pyi
yt_dlp-stubs/__init__.pyi
yt_dlp-stubs/aes.pyi
yt_dlp-stubs/cache.pyi
yt_dlp-stubs/cookies.pyi
yt_dlp-stubs/globals.pyi
yt_dlp-stubs/jsinterp.pyi
yt_dlp-stubs/minicurses.pyi
yt_dlp-stubs/options.pyi
yt_dlp-stubs/plugins.pyi
yt_dlp-stubs/py.typed
yt_dlp-stubs/socks.pyi
yt_dlp-stubs/update.pyi
yt_dlp-stubs/version.pyi
yt_dlp-stubs/webvtt.pyi
yt_dlp-stubs/compat/__init__.pyi
yt_dlp-stubs/compat/compat_utils.pyi
yt_dlp-stubs/compat/imghdr.pyi
yt_dlp-stubs/downloader/__init__.pyi
yt_dlp-stubs/downloader/bunnycdn.pyi
yt_dlp-stubs/downloader/common.pyi
yt_dlp-stubs/downloader/dash.pyi
yt_dlp-stubs/downloader/external.pyi
yt_dlp-stubs/downloader/f4m.pyi
yt_dlp-stubs/downloader/fc2.pyi
yt_dlp-stubs/downloader/fragment.pyi
yt_dlp-stubs/downloader/hls.pyi
yt_dlp-stubs/downloader/http.pyi
yt_dlp-stubs/downloader/ism.pyi
yt_dlp-stubs/downloader/mhtml.pyi
yt_dlp-stubs/downloader/niconico.pyi
yt_dlp-stubs/downloader/rtmp.pyi
yt_dlp-stubs/downloader/rtsp.pyi
yt_dlp-stubs/downloader/websocket.pyi
yt_dlp-stubs/downloader/youtube_live_chat.pyi
yt_dlp-stubs/extractor/__init__.pyi
yt_dlp-stubs/extractor/common.pyi
yt_dlp-stubs/extractor/commonmistakes.pyi
yt_dlp-stubs/extractor/commonprotocols.pyi
yt_dlp-stubs/networking/__init__.pyi
yt_dlp-stubs/networking/_helper.pyi
yt_dlp-stubs/networking/common.pyi
yt_dlp-stubs/networking/exceptions.pyi
yt_dlp-stubs/networking/impersonate.pyi
yt_dlp-stubs/networking/websocket.pyi
yt_dlp-stubs/postprocessor/__init__.pyi
yt_dlp-stubs/postprocessor/common.pyi
yt_dlp-stubs/utils/__init__.pyi
yt_dlp-stubs/utils/_deprecated.pyi
yt_dlp-stubs/utils/_jsruntime.pyi
yt_dlp-stubs/utils/_legacy.pyi
yt_dlp-stubs/utils/_utils.pyi
yt_dlp-stubs/utils/networking.pyi
yt_dlp-stubs/utils/progress.pyi
yt_dlp-stubs/utils/traversal.pyi
yt_dlp-stubs/utils/jslib/__init__.pyi
yt_dlp-stubs/utils/jslib/devalue.pyi
types_yt_dlp-2026.1.29.20260131.dist-info/METADATA
types_yt_dlp-2026.1.29.20260131.dist-info/WHEEL
types_yt_dlp-2026.1.29.20260131.dist-info/top_level.txt
types_yt_dlp-2026.1.29.20260131.dist-info/RECORD
